aiocouch/__init__.py
aiocouch/attachment.py
aiocouch/bulk.py
aiocouch/couchdb.py
aiocouch/database.py
aiocouch/design_document.py
aiocouch/document.py
aiocouch/event.py
aiocouch/exception.py
aiocouch/py.typed
aiocouch/remote.py
aiocouch/request.py
aiocouch/typing.py
aiocouch/view.py
aiocouch-4.0.1.dist-info/licenses/LICENSE
aiocouch-4.0.1.dist-info/METADATA
aiocouch-4.0.1.dist-info/WHEEL
aiocouch-4.0.1.dist-info/top_level.txt
aiocouch-4.0.1.dist-info/RECORD
